dxskytap/__init__.py
dxskytap/attached_vpns.py
dxskytap/vpns.py
dxskytap/users.py
dxskytap/tags.py
dxskytap/publish_sets.py
dxskytap/vms.py
dxskytap/interfaces.py
dxskytap/projects.py
dxskytap/settings.py
dxskytap/reports.py
dxskytap/configurations.py
dxskytap/restobject.py
dxskytap/connect.py
dxskytap/stateful.py
dxskytap/networks.py
dxskytap/hardware.py
dxskytap/assets.py
dxskytap/templates.py
dxskytap/tunnels.py
dxskytap/assignableobject.py
dxskytap-1.0.0.dist-info/metadata.json
dxskytap-1.0.0.dist-info/WHEEL
dxskytap-1.0.0.dist-info/METADATA
dxskytap-1.0.0.dist-info/top_level.txt
dxskytap-1.0.0.dist-info/DESCRIPTION.rst
dxskytap-1.0.0.dist-info/RECORD
