Metadata-Version: 2.0
Name: dxskytap
Version: 1.0.0
Summary: DataXu Utilities for Skytap
Home-page: http://www.dataxu.com
Author: DataXu
Author-email: rcarey@dataxu.com
License: BSD-new
Keywords: skytap cloud client rest api development
Platform: UNKNOWN
Classifier: Development Status :: 5 - Production/Stable
Classifier: Intended Audience :: Developers
Classifier: License :: OSI Approved :: BSD License
Classifier: Natural Language :: English
Classifier: Operating System :: POSIX :: Linux
Classifier: Programming Language :: Python :: 2.4
Classifier: Programming Language :: Python :: 2.5
Classifier: Programming Language :: Python :: 2.6
Classifier: Programming Language :: Python :: 2.7
Classifier: Programming Language :: Python :: 3
Classifier: Topic :: Software Development :: Libraries
Requires-Dist: httplib2 (>=0.8)
Requires-Dist: pexpect (>=2.4)
